sir_utilities/__init__.py
sir_utilities/background_scheduler_util.py
sir_utilities/cli.py
sir_utilities/date_time.py
sir_utilities/env_reader.py
sir_utilities/find_root.py
sir_utilities/logger.py
sir_utilities/main_helper.py
sir_utilities/memory_tracer.py
sir_utilities/py.typed
sir_utilities/run_group.py
sir_utilities/system_metrics.py
sir_utilities/thread_helper.py
sir_utilities/unit_conversion.py
sir_utilities-0.1.5.dist-info/METADATA
sir_utilities-0.1.5.dist-info/WHEEL
sir_utilities-0.1.5.dist-info/RECORD
