Metadata-Version: 2.1
Name: sir-utilities
Version: 0.1.5
Summary: A collection of personal tools, utilities and helpers.
Author: sirEven
Author-email: sir_even@icloud.com
Requires-Python: >=3.10,<4
Classifier: Programming Language :: Python :: 3
Classifier: Programming Language :: Python :: 3.10
Classifier: Programming Language :: Python :: 3.11
Classifier: Programming Language :: Python :: 3.12
Requires-Dist: python-dotenv (>=1.0.0,<2.0.0)
